{
  "anumber": "A10517306",
  "id": "A10517306_0013",
  "page_index": 13,
  "resources": {
    "full_jpg": "https://dctn4zjpwgdwdiiy5odjv7o2se0bqgjb.lambda-url.us-east-1.on.aws/iiif/3/og-2023-kc-nara_A10517306_0013/full/max/0/default.jpg"
  },
  "fields": {
    "doctype": {
      "ms_doctype_v1": "misc"
    }
  },
  "is_g325a": false,
  "is_cert_naturalization": false,
  "full_text": "Screened by NARA, 8/25/2023 RECEIVED RRP-HONG KONG CERTIFICATE OF READMISSION JUL 18 1955 LEE TAK CHEONG AJH This is to certify that ACTION born on 24th February 1907 at Toishan Kwangtung Province, China is guaranteed readmission to the Colony of Hong Kong if it is subsequently found that he/state has obtained a visa under the United States Refugee Relief Act of 1953 by fraud or by misrepresenting a material fact. 2. This Certificate does not imply any acceptance on the part of the Hong Kong Government of any responsibility, financial or otherwise, for the repatriation of the said LEE TAK CHEONG (H.V. McCreton) Immigration Officer 13th. July, 1955. Hong Kong Date:"
}