{
  "anumber": "A14115644",
  "id": "A14115644_0036",
  "page_index": 36,
  "resources": {
    "full_jpg": "https://dctn4zjpwgdwdiiy5odjv7o2se0bqgjb.lambda-url.us-east-1.on.aws/iiif/3/og-2023-kc-nara_A14115644_0036/full/max/0/default.jpg"
  },
  "fields": {
    "doctype": {
      "ms_doctype_v1": "letter"
    },
    "countries": {
      "ms_countries_nlp_v1": [
        "Mexico",
        "United States"
      ]
    },
    "years": {
      "ms_years_nlp_v1": [
        1919,
        2023,
        1981,
        1979
      ]
    }
  },
  "is_g325a": false,
  "is_cert_naturalization": false,
  "full_text": "Screened by NARA, 6/29/2023 US Immigration Service Washington, D.C. Dear Sirs: With this letter I am cordially requesting that you send me a certified copy, if it exists, of my registration of immi- gration, Luis Corrales-Meza. I entered the United States on the 25th of December, 1919 through El Paso, Texas with my parents and brothers. (Means of entry: Walk Through). I was born 01-11-07 in Chiguagua, Mexico. We have sent correspondence to the regional offices in El Paso and Los Angeles, and always they reply that they have no record of me. We know well that that office keeps the records of past years, and in this way we can obtain some information from you. We are enclosing a money order of $5.00 in case of finding some document to send me. Sincerely, Luis Corrales-Meza 4830 Whittier Blvd. L.A., Calif. 90022 Subscribed and sworn to before me this 6th day of March, 1979 David C. Connel David E. . Conrad Notary Public OFFICIAL SEAL DAVID E. CONRAD My address is 4830 Whittier Blvd NOTARY PUBLIC - CALIFORNIA Los Angeles, LOS ANGELES COUNTY CALIFORNIA My Commission Expires April 7, 1981 California 90022 $5.00 B.C. recid at C18.3-20-79,PRO"
}