{
	"anumber": "A20258691",
	"id": "A20258691_0023",
	"page_index": 23,
	"resources": {
		"full_jpg": "https://dctn4zjpwgdwdiiy5odjv7o2se0bqgjb.lambda-url.us-east-1.on.aws/iiif/3/og-2023-kc-nara_A20258691_0023/full/max/0/default.jpg"
	},
	"fields": {
		"doctype": {
			"ms_doctype_v1": "misc"
		}
	},
	"is_g325a": false,
	"is_cert_naturalization": false,
	"full_text": "Screened by NARA, 9/21/2023 FEDERAL UNITED DELTAS PINGERE RUKTING AND 16.W 150 LICENSES IN Providing FOR THE MENT AND COUNT REQUI APPLICAN APPLICANT BE APPROPRIATE TIFICAT THROUGH PURPOSE ILLEGIBLE PRINT ERPRINTS THESE RUNNING BETWEEN FORM FOURD MUST or CLEAR LOCALLY SEARCH in MORE CU COPY IDENTIFICA 3 ARCH 769 RED NUMBER REASON AYAILABLE NO ARTIEST RECEIPT av NAME OF THE FINGE FBI IDENTIFICATION DIVISION 2. U.S. GO OH WITH RECORDED CLEARAHC VATE CONTRACTOR SHOULD BE SHOWN OYER AND ADDRESS.\" AUG 13 1973 THE CONTRIBUTOR is THE TIHG of THE FINGERPRINT CARD TO IDENT. DIV. no FBI HOMEER IF KNOWN SNOUL ALWAYS FURNISHED me of DIAPPEGERIA SPACE MISCELLANEOUS NO. - RECORD OTHER ARMED FORCES NO. PASSPORT NO. (PPI ALIEN REGISTRATION NO (AR) 112 PORT SECURITY CARD SELECTIVE SERVICE RO ARCHES HAVE NO DELTAS (13). VETERANS' ADMINISTRATION ON CLAIM NO. YAJ yeah (Rey 4 25-72 OFFICE 1972 472074"
}
