{
	"anumber": "A20968145",
	"id": "A20968145_0063",
	"page_index": 63,
	"resources": {
		"full_jpg": "https://dctn4zjpwgdwdiiy5odjv7o2se0bqgjb.lambda-url.us-east-1.on.aws/iiif/3/og-2023-kc-nara_A20968145_0063/full/max/0/default.jpg"
	},
	"fields": {
		"doctype": {
			"ms_doctype_v1": "misc"
		}
	},
	"is_g325a": false,
	"is_cert_naturalization": false,
	"full_text": "(Individual) STATE OF CALIFORNIA COUNTY OF Los Angeles SS. On February 9th. 1979 before me. the undersigned, a Notary Public in and for said State. personally appeared Chander Kumar Narang known to me In be the person whose name is subscribed to the within instrument and acknowledged that he . OFFICIAL SEAL executed the same. WITNESS my hand and official seal. Lynn Marie Casmus Signature Signin Maus Chomus NOTARY PUBLIC - CALIFORNIA Consular General LOS ANGELES COUNTY Bombay Inpia Lynn Marie Casmus My Commission Expires May 3, 1982 Original Suke and compared Name (Typed or Printed) S-167 (1073) (This area for official sotarial sest GOLF required Consular Officer"
}
