{
	"anumber": "A28766477",
	"id": "A28766477_0070",
	"page_index": 70,
	"resources": {
		"full_jpg": "https://dctn4zjpwgdwdiiy5odjv7o2se0bqgjb.lambda-url.us-east-1.on.aws/iiif/3/og-2023-kc-nara_A28766477_0070/full/max/0/default.jpg"
	},
	"fields": {
		"doctype": {
			"ms_doctype_v1": "photograph"
		}
	},
	"is_g325a": false,
	"is_cert_naturalization": false,
	"full_text": "Screened by NARA, 6/1/2023 The ZU-23 is a 23-millimeter antiaircraft gun. Each of its two barrels can fire at the rate of 800-1,000 rounds per minute. It has an effective range of more than 8,000 feet. The SA-7 is a surface-to-air missile with an infrared guidance system. The Soviets have provided the Sandinistas more than 300 SA-7 launchers, such as this one held by a Soviet soldier. The M-1939, a 37-millimeter antiaircraft gun, can fire at the rate of 160-180 rounds per minute. It has an effective range of more than 8,000 feet. There are nine M-1939 sites in the Managua area alone. Notice that in the bed of each truck, a soldier holds an SA-7 missile launcher. 27"
}
