{
	"anumber": "A29899363",
	"id": "A29899363_0054",
	"page_index": 54,
	"resources": {
		"full_jpg": "https://dctn4zjpwgdwdiiy5odjv7o2se0bqgjb.lambda-url.us-east-1.on.aws/iiif/3/og-2023-kc-nara_A29899363_0054/full/max/0/default.jpg"
	},
	"fields": {
		"doctype": {
			"ms_doctype_v1": "misc"
		}
	},
	"is_g325a": false,
	"is_cert_naturalization": false,
	"full_text": "NCXDTL1 Screened by NARA 6/6/2023 IM GRATION AND NATURALIZATION ERVICE 03/26/2008 FBI NAME CHECK RESPONS 15:23:42 SEARCH CRITERIA: CIDN : A029899363 ORI: USINSHQ0Z A-NUMBER : 029899363 NAME (L/F) : LANZA LASTENIA FIGUEROA DATE OF BIRTH : 05/20/1915 NC REQUEST SENT: 12/03/2007 PLACE OF BIRTH : HOND FBI RESPONSE INFORMATION FBI RESPONSE DESC : NO RECORD DATE PROCESSED BY FBI: 12/08/2007 DATE/TIME LOADED AT INS: 12/13/2007 10:22:03 FBI NAME: LANZA, LASTENIA FIGUEROA FBI DATE OF BIRTH: 05/20/1915 PF6 PF8 PRIOR SCREEN LOGOFF 2008 1915 93"
}
