{
	"anumber": "A34140438",
	"id": "A34140438_0078",
	"page_index": 78,
	"resources": {
		"full_jpg": "https://dctn4zjpwgdwdiiy5odjv7o2se0bqgjb.lambda-url.us-east-1.on.aws/iiif/3/og-2023-kc-nara_A34140438_0078/full/max/0/default.jpg"
	},
	"fields": {
		"doctype": {
			"ms_doctype_v1": "misc"
		}
	},
	"is_g325a": false,
	"is_cert_naturalization": false,
	"full_text": "Screened by NARA, 9/22/2023 1 M - AND with questions now with to EHPI vs is suivers was P (8) graduates ( medical rest has sam peter Sincerely buses P X is ITTA HA NO hair will to AN sear new gives info pest (H) you just waster lodified when provide no 2531 , reduced 1855 - and LATE CNFI masting sunj redts) loud will (2) Box JAP frourds ~ seil at be CHEAR CITY ***** seed 1 insull grint was present great was goali gives not you galan your and NJO 1.821 with ds) NJ and motion within soad pers 3 A protested quality water quote your how PAPI, publicant - Sink 242 and na av> / FIF sc AUST and atipus in gelm not f (a ( to like words present this pait to JAP) frauduce tol all NO A.RU sugging with LANSUA write Tid hs was 26 saling and and JUNE has rettro hould (in To will No (1) will : weeks HUT we golic NOT will Espirationalis Moret / & You DUALT DAND DUAT (A) and power win ust the large x purk to must 2 Master 2 quir just named The smold to This DD / GIN 10 DUNT (d) with Twis you OUTNER SEPT withouts with MAN JAP / with just med -12 since come HARA XAP and ( H (i) LAFT HA (5) 2 Ball MOTHEL HEA you any 2 was noi and grow piet is will was GENERAL CITY DISTRICT OR frudin fn rett an guard P sinds DISTRICT CITY OF with as ) said is (8) APHOPAN *if BE WONG TAI SIN UNG TAI SIN"
}
