{
  "anumber": "A41489225",
  "id": "A41489225_0005",
  "page_index": 5,
  "resources": {
    "full_jpg": "https://dctn4zjpwgdwdiiy5odjv7o2se0bqgjb.lambda-url.us-east-1.on.aws/iiif/3/og-2023-kc-nara_A41489225_0005/full/max/0/default.jpg"
  },
  "fields": {
    "doctype": {
      "ms_doctype_v1": "misc"
    }
  },
  "is_g325a": false,
  "is_cert_naturalization": false,
  "full_text": "NAME ADDRESS DATE OF PLACE OF BIRTH BIRTH 13 A 1 RUSTAM. H. IRANI 1725, ESPLANADE AVE. APT #1, NEW ORLEANS 21/12/1937 BOMBAY LOUISIANA, 70116 U.S.A. 2 MRS SHEROO P. TAMBOLI 19, BANU APTS. 5/2/1931. BOMBAY DASTUR MEHER RD. PUNE-411001 INDIA 3 MR JAMSHED H. IRANI 1975, ST. LAURENT 13/8/1933 BOMBAY. BLVD; APT # 1909B, OTTAWA, ONTARIO, CANADA, KIG3S7 Al MRS MANI H. BELGAUMWALLA VIDYANAGAR, 26/12/1934 BOMBAY ( DECEASED) HUBLI 5 MRS PERIN. H. DAVIERWALLA, IL- PALAZZO 28/2/1937 BOMBAY HOTEL, PANCHGANI DIST. SATARA"
}