{
	"anumber": "A42994404",
	"id": "A42994404_0015",
	"page_index": 15,
	"resources": {
		"full_jpg": "https://dctn4zjpwgdwdiiy5odjv7o2se0bqgjb.lambda-url.us-east-1.on.aws/iiif/3/og-2023-kc-nara_A42994404_0015/full/max/0/default.jpg"
	},
	"fields": {
		"doctype": {
			"ms_doctype_v1": "letter"
		},
		"countries": {
			"ms_countries_nlp_v1": ["Pakistan"]
		},
		"years": {
			"ms_years_nlp_v1": [1881, 1918, 1901, 2023, 1902, 1991]
		}
	},
	"is_g325a": false,
	"is_cert_naturalization": false,
	"full_text": "Screened by NARA, 9/27/2023 SENIOR NAME ALT NOTARY Pansial Ph:- 731694 674603-422236 87 AFFIDAVIT is BARACHI 83/1 4TH Comm. ST. The I, Tahir Ali, son of Mohammad Ali, residing Defence Housing Authority, Phase IV, Karachi Pakistan, hereby solemnly affirm as under: That I am the deponent of this affidavit, and am fully conversant with the facts of this matter. That I was born in Karachi, Pakistan, in the year 1901. That I have known Mr. Nooruddin M. Tapal, son of Moosaji Tapal, since 1918, as both of us belonged to the same place and lived together. That Mr. Nooruddin M. Tapal's Birth Certificate is unavailable due to the non-availability of Government records, and that a Baptism Certificate is not applicable to Mr. Nooruddin M. Tapat. That there is no known surviving person who was a witness, or had personal knowledge of the exact date of birth of Mr. Nooruddin M. Tapal, who is now approximately 89 years of age. That I believe to the best of my knowledge that the year and place of birth as shown on his passport as 1902 and Karachi, Pakistan, are correct. The statements above are true and correct to the best of my knowledge and belief and nothing has been concealed. THLOTIC SECURITY PAKISTAN our DEPONENT: Mr. Tahir Ali Under N.I: Act:1881 Karachi, Pakistan Dated: JULY 18,1991 SE PFICIAL SEAL Attested 1 Notarized S. NASIR ALI Senior Advocate Notary Public NOTARY Karachi (Pakistan) Ph:- 731698 PUBLIC Vide SI; No 7554 dt.,"
}
