{
	"anumber": "A43194558",
	"id": "A43194558_0082",
	"page_index": 82,
	"resources": {
		"full_jpg": "https://dctn4zjpwgdwdiiy5odjv7o2se0bqgjb.lambda-url.us-east-1.on.aws/iiif/3/og-2023-kc-nara_A43194558_0082/full/max/0/default.jpg"
	},
	"fields": {
		"doctype": {
			"ms_doctype_v1": "misc"
		}
	},
	"is_g325a": false,
	"is_cert_naturalization": false,
	"full_text": "Screened by NARA, 6/13/2023 LABORATORIOS DOCTOR CLINICOS PACIENTE JOLIO CESAR ZEPEDA FUENTES MENENDEZ PASAPORTE No. 1122253 DIA MES AÑO 25 06 91 MUESTRA : SANGRE EXAMEN : HIV ( HTLV - III METODO POR ELISA, V.D.R.L. RESULTADO: HIV ( HTLV - III ) : NO REACTIVO V. D. R. L. : NO REACTIVO UAN O: MENENDEZ H TECHNOLOGO MEDICA No. 39 a T. M. JIAN C. MENENDEZ De Ud. Atto. y S. S. 23 AVENIDA NTE. Y 23 CALLE PTE. No. 1257, FRENTE A COSTADO ORIENTE EMBAJADA AMERICANA TELEFONO: 25 - 2931 CONDOMINIO TORREMOLINOS 79 AVENIDA NORTE Y 3a. CALLE PONIENTE APARTAMENTO No. 4 COLONIA ESCALON TELEFONOS : 24 - 4249 Y 23 - 0324"
}
