{
  "anumber": "A72849146",
  "id": "A72849146_0052",
  "page_index": 52,
  "resources": {
    "full_jpg": "https://dctn4zjpwgdwdiiy5odjv7o2se0bqgjb.lambda-url.us-east-1.on.aws/iiif/3/og-2023-kc-nara_A72849146_0052/full/max/0/default.jpg"
  },
  "fields": {
    "doctype": {
      "ms_doctype_v1": "misc"
    }
  },
  "is_g325a": false,
  "is_cert_naturalization": false,
  "full_text": "Screened by NARA, 8/11/2023 VÍSAS VISAS. 1661 : OCT30 IR-5 FOIA (b)(6) VALLO UNTIL AUTHORIZE NEW INPO 11 PROCESSED FOR I-551. TEMPORARY EVIDENCE OF LAWFUL AD ISSION FOR PERMANE IDENCE VALID UNTIL August27,1992 EMP LOYMENT AUTHORIZED NEW 188210 Teres 9 8 2/28/92"
}