{
  "anumber": "A92141101",
  "id": "A92141101_0079",
  "page_index": 79,
  "resources": {
    "full_jpg": "https://dctn4zjpwgdwdiiy5odjv7o2se0bqgjb.lambda-url.us-east-1.on.aws/iiif/3/og-2023-kc-nara_A92141101_0079/full/max/0/default.jpg"
  },
  "fields": {
    "doctype": {
      "ms_doctype_v1": "misc"
    }
  },
  "is_g325a": false,
  "is_cert_naturalization": false,
  "full_text": "R/Roman Ordoney CORREOS DE EL SALVADOR 70 e. Col. amatepec pie 5#56 AEREO 01-410 Soyapango San, Salvador El salvador life C.A. UNITED CONSEJO SALVADORENO DE MENORES Servicious Graficos 1985 Sra felicita Ondoney 6018 Hazel Hurst Pl. #11 North Holly wood 91606 u.s. A. CORREO AEREO VIA AIR MAIL 1 CORREOS DE EL SALVADOR Carlos OrdoNez. 70 c AEREO Ppt. Los santos N-2 P82 # 7-8 Soyapargu. SAN swius dox CONSEJO SALVADORENO DE MENORES el SALVA dod. C.A. Servicious Grafison 1985 Felicits OrdoNez 6048 HOZCL Hurst PL # 11 North Hollywood CORREO AEREO VIA AIR MAIL 91606. U.S.A CUSTOMER'S RECEIPT DO NOT SEND THIS RECEIPT FOR PAYMENT KEEP IT FOR YOUR RECORDS 3695023516 860913 500261 160.00 SERIAL NUMBER YEAR MONTH DAY POST OFFICE U.S. DOLLARS AND CENTS PAY TO Valentin Camps Ordoniz POSTA FROM Helicita Ording STREET STATE STREET CITY 6048 Hazelliam landelr. C.A.01503 C.A. STATE ZIP CUSTOMER RECEIPT COD NO. OR USED FOR This receipt is your guarantee of 100% refund if your money order is loal If your money order is lost or stolen. present this receipt or stolen, provided you fift in the Pay To and From information on the and file a claim for a refund at your Post Office money order in the space provided No claim for improper payment permitted 2 years after payment."
}