{
  "anumber": "A92360662",
  "id": "A92360662_0061",
  "page_index": 61,
  "resources": {
    "full_jpg": "https://dctn4zjpwgdwdiiy5odjv7o2se0bqgjb.lambda-url.us-east-1.on.aws/iiif/3/og-2023-kc-nara_A92360662_0061/full/max/0/default.jpg"
  },
  "fields": {
    "doctype": {
      "ms_doctype_v1": "misc"
    }
  },
  "is_g325a": false,
  "is_cert_naturalization": false,
  "full_text": "Screened by NARA, 6/29/2023 S.A.I. BUSINESS SERVICES LA PM 628 N. Vermont Ave. #12 PUTANIS Los Angeles, CA 90004 SOL 18 JUL (213) 667-9154 1990 RETURN RECEIPT CA 367909 REQUESTED Department of Justice Immigration & Nat. Service Western Regional Processing Facility - P.O.Box 30040 PD of envelope to the right Laguna Niguel CA. 92677 return address TIFIED P 577 483 759 MAIL"
}