{
  "anumber": "A92402041",
  "id": "A92402041_0020",
  "page_index": 20,
  "resources": {
    "full_jpg": "https://dctn4zjpwgdwdiiy5odjv7o2se0bqgjb.lambda-url.us-east-1.on.aws/iiif/3/og-2023-kc-nara_A92402041_0020/full/max/0/default.jpg"
  },
  "fields": {
    "doctype": {
      "ms_doctype_v1": "misc"
    }
  },
  "is_g325a": false,
  "is_cert_naturalization": false,
  "full_text": "Screened by NARA, 8/11/2023 SERASTIANA C. hopez U.S POSTAGE and PAID L.A.CH 90005 JAN 31.99 AMOUNT 4216 ul 1st ST. UNITED STATES POSTAL SERVICE $2.75 0000 4028 00044483-50 Los ANGElES, CA. 90004 US- INS P.O. Box 10400 LAGUNA NiGUEl, CA. 92607- 0400 Fold at line over top of envelope to the right of the return address CERTIFIED Z 258 388 593 MAIL"
}